Metadata-Version: 2.1
Name: atd-knack-util
Version: 0.0.3
Summary: Python utilities for interacting with Knack applications.
Home-page: https://github.com/cityofaustin/atd-data-utilities/tree/master/atd-knack-util
Author: City of Austin
Author-email: transportation.data@austintexas.gov
License: UNKNOWN
Platform: UNKNOWN
Classifier: Programming Language :: Python :: 3
Classifier: License :: Public Domain
Classifier: Operating System :: OS Independent
Classifier: Development Status :: 4 - Beta
Requires-Dist: arrow
